Workbook
Name Slicer_Category: #N/A
Name Slicer_Region: #N/A
Name Slicer_Segment: #N/A
Name Slicer_Year: #N/A

Sheet Executive

Sheet Operational

Sheet Customers 
M13: Name | P13: Total Spend | R13: Days Since Last Order
M14: ='Pivot Tables'!B95 -> Lauren Leatherbury | P14: ='Pivot Tables'!C95 -> 2741.204 | R14: =DATE(2018,12,31) - 'Pivot Tables'!D95 -> 250
M15: ='Pivot Tables'!B96 -> John Lucas | P15: ='Pivot Tables'!C96 -> 2725.256 | R15: =DATE(2018,12,31) - 'Pivot Tables'!D96 -> 615
M16: ='Pivot Tables'!B97 -> Bill Overfelt | P16: ='Pivot Tables'!C97 -> 2682.728 | R16: =DATE(2018,12,31) - 'Pivot Tables'!D97 -> 138
M17: ='Pivot Tables'!B98 -> Nicole Hansen | P17: ='Pivot Tables'!C98 -> 2673.29 | R17: =DATE(2018,12,31) - 'Pivot Tables'!D98 -> 190
M18: ='Pivot Tables'!B99 -> Beth Thompson | P18: ='Pivot Tables'!C99 -> 2567.656 | R18: =DATE(2018,12,31) - 'Pivot Tables'!D99 -> 337
M19: ='Pivot Tables'!B100 -> Eleni Mccrary | P19: ='Pivot Tables'!C100 -> 2567.01 | R19: =DATE(2018,12,31) - 'Pivot Tables'!D100 -> 133
M20: ='Pivot Tables'!B101 -> Mary Zewe | P20: ='Pivot Tables'!C101 -> 2564.906 | R20: =DATE(2018,12,31) - 'Pivot Tables'!D101 -> 283
M21: ='Pivot Tables'!B102 -> Deanra Eno | P21: ='Pivot Tables'!C102 -> 2550.874 | R21: =DATE(2018,12,31) - 'Pivot Tables'!D102 -> 719
M22: ='Pivot Tables'!B103 -> Amy Hunt | P22: ='Pivot Tables'!C103 -> 2495.3916 | R22: =DATE(2018,12,31) - 'Pivot Tables'!D103 -> 231
M23: ='Pivot Tables'!B104 -> Charles Crestani | P23: ='Pivot Tables'!C104 -> 2471.65 | R23: =DATE(2018,12,31) - 'Pivot Tables'!D104 -> 107

Sheet Pivot Tables
B3: Total Revenue | D3: Total Profit | F3: #Orders | H3: Avg. Order Value | J3: Row Labels | K3: #Customer
B4: 2297200.9 | D4: 286397.02 | F4: 5009 | H4: 458.61467 | J4: Recent Customers | K4: 104
B6: Avg. Selling Price | D6: YoY Growth | F6: Avg. Spend per Customer | H6: Total Quantity | J6: Row Labels | K6: #Customer
B7: 60.655371 | D7: 0.43266271 | F7: 2896.8485 | H7: 37873 | J7: Loyal Customers | K7: 247
B9: Profit Margin | D9: Avg. Days to Ship | F9: #Products | H9: #Customer | J9: Row Labels | K9: #Customer
B10: 0.12467217 | D10: 3.9584751 | F10: 1862 | H10: 793 | J10: At Risk | K10: 179
P14: Segment | Q14: Champions
B15: Row Labels | C15: Total Revenue | D15: Total Revenue2 | F15: Segments | G15: Total Revenue
B16: January | C16: 109456.69 | D16: 109456.69 | F16: Consumer | G16: 1161401.3 | I16: Row Labels | J16: Growth Rate | K16: Growth Rate2 | P16: Row Labels | Q16: Total Revenue
B17: February | C17: 68546.472 | D17: 68546.472 | F17: Corporate | G17: 706146.37 | I17: 2015 | J17: 0 | K17: 0 | L17: =I17 -> 2015 | M17: =J17 -> 0 | N17: =M17 -> 0 | P17: Phones | Q17: 105948.85
B18: March | C18: 191665.31 | D18: 191665.31 | F18: Home Office | G18: 429653.15 | I18: 2016 | J18: 0.019259423 | K18: 0.019259423 | L18: =I18 -> 2016 | M18: =J18 -> 0.019259423 | N18: =M18 -> 0.019259423 | P18: Chairs | Q18: 90549.216
B19: April | C19: 136953.7 | D19: 136953.7 | F19: Grand Total | G19: 2297200.9 | I19: 2017 | J19: 0.27507626 | K19: 0.27507626 | L19: =I19 -> 2017 | M19: =J19 -> 0.27507626 | N19: =M19 -> 0.27507626 | P19: Binders | Q19: 68852.646
B20: May | C20: 146361.95 | D20: 146361.95 | I20: 2018 | J20: 0.19558143 | K20: 0.19558143 | L20: =I20 -> 2018 | M20: =J20 -> 0.19558143 | N20: =M20 -> 0.19558143 | P20: Storage | Q20: 62000.508
B21: June | C21: 161335.71 | D21: 161335.71 | I21: Grand Total | J21: 0.46817349 | K21: 0.46817349 | P21: Tables | Q21: 52648.575
B22: July | C22: 148170.64 | D22: 148170.64 | P22: Grand Total | Q22: 379999.79
B23: August | C23: 154153.16 | D23: 154153.16 | F23: Region | G23: Total Revenue
B24: September | C24: 304631.16 | D24: 304631.16 | F24: West | G24: 764634.45
B25: October | C25: 204727.05 | D25: 204727.05 | F25: East | G25: 611734.3
B26: November | C26: 330681.74 | D26: 330681.74 | F26: Central | G26: 518800.13
B27: December | C27: 340517.29 | D27: 340517.29 | F27: South | G27: 402031.98 | K27: Row Labels | L27: #Customer
B28: Grand Total | C28: 2297200.9 | D28: 2297200.9 | F28: Grand Total | G28: 2297200.9 | K28: Loyal Customers | L28: 247
K29: At Risk | L29: 179
K30: Champions | L30: 116
K31: Recent Customers | L31: 104
K32: Big Spenders | L32: 85
K33: Needs Attention | L33: 62
B34: Row Labels | C34: #Orders | D34: Avg Days to Ship | K34: Grand Total | L34: 793
B35: Same Day | C35: 264 | D35: 0.044198895
B36: First Class | C36: 787 | D36: 2.1820546
B37: Second Class | C37: 964 | D37: 3.2380463
B38: Standard Class | C38: 2994 | D38: 5.0072051
B39: Grand Total | C39: 5009 | D39: 3.9584751 | G39: Row Labels | H39: Total Revenue | I39: Total Profit
G40: Furniture | H40: 741999.8 | I40: 18451.273
G41: Office Supplies | H41: 719047.03 | I41: 122490.8
G42: Technology | H42: 836154.03 | I42: 145454.95
G43: Grand Total | H43: 2297200.9 | I43: 286397.02
B45: Row Labels | C45: Total Profit | D45: State | E45: Total Profit
B46: California | C46: 59398.313 | D46: {=B46:C87} -> California | E46: 59398.313
B47: New York | C47: 58177.834 | D47: New York | E47: 58177.834
B48: Washington | C48: 24405.797 | D48: Washington | E48: 24405.797
B49: Texas | C49: 20528.911 | D49: Texas | E49: 20528.911
B50: Pennsylvania | C50: 13604.935 | D50: Pennsylvania | E50: 13604.935
B51: Georgia | C51: 12781.343 | D51: Georgia | E51: 12781.343
B52: Arizona | C52: 9563.2001 | D52: Arizona | E52: 9563.2001
B53: Illinois | C53: 9560.1456 | D53: Illinois | E53: 9560.1456
B54: Wisconsin | C54: 8569.8697 | D54: Wisconsin | E54: 8569.8697
B55: Michigan | C55: 7752.2969 | D55: Michigan | E55: 7752.2969
B56: Minnesota | C56: 7202.5225 | D56: Minnesota | E56: 7202.5225
B57: Virginia | C57: 6940.1112 | D57: Virginia | E57: 6940.1112
B58: Ohio | C58: 5985.887 | D58: Ohio | E58: 5985.887
... B60: Kentucky | C60: 4513.314 | D60: Kentucky | E60: 4513.314
B61: Tennessee | C61: 3434.2765 | D61: Tennessee | E61: 3434.2765 | K61: Row Labels | L61: Total Profit
B62: Delaware | C62: 3336.3827 | D62: Delaware | E62: 3336.3827 | K62: Copiers | L62: 55617.825
B63: Alabama | C63: 2845.0624 | D63: Alabama | E63: 2845.0624 | K63: Phones | L63: 44515.731
B64: Indiana | C64: 2707.3495 | D64: Indiana | E64: 2707.3495 | G64: Row Labels | H64: Total Profit | K64: Accessories | L64: 41936.636
B65: Louisiana | C65: 2659.2401 | D65: Louisiana | E65: 2659.2401 | G65: Tables | H65: -17725.481 | K65: Paper | L65: 34053.569
B66: New Jersey | C66: 2336.7532 | D66: New Jersey | E66: 2336.7532 | G66: Bookcases | H66: -3472.556 | K66: Binders | L66: 30221.763
B67: Rhode Island | C67: 2276.7013 | D67: Rhode Island | E67: 2276.7013 | G67: Supplies | H67: -1189.0995 | K67: Grand Total | L67: 206345.52
B68: Iowa | C68: 2258.5883 | D68: Iowa | E68: 2258.5883
B69: Missouri | C69: 2212.8747 | D69: Missouri | E69: 2212.8747
B70: Utah | C70: 1818.1938 | D70: Utah | E70: 1818.1938 | G70: Row Labels | H70: Total Revenue | I70: Max Order Date | K70: Customer | L70: Sales | M70: Recency
B71: New Hampshire | C71: 1519.1696 | D71: New Hampshire | E71: 1519.1696 | G71: Adam Bellavance | H71: 7755.62 | I71: 43410 | K71: =G71 -> Adam Bellavance | L71: =H71 -> 7755.62 | M71: =DATE(2018,12,31)-I71 -> 55
B72: New Mexico | C72: 1340.1399 | D72: New Mexico | E72: 1340.1399 | G72: Adrian Barton | H72: 14473.571 | I72: 43423 | K72: =G72 -> Adrian Barton | L72: =H72 -> 14473.571 | M72: =DATE(2018,12,31)-I72 -> 42
B73: Nebraska | C73: 1166.0176 | D73: Nebraska | E73: 1166.0176 | G73: Alan Dominguez | H73: 6106.88 | I73: 43435 | K73: =G73 -> Alan Dominguez | L73: =H73 -> 6106.88 | M73: =DATE(2018,12,31)-I73 -> 30
B74: Colorado | C74: 970.4647 | D74: Colorado | E74: 970.4647 | G74: Alex Avila | H74: 5563.56 | I74: 43280 | K74: =G74 -> Alex Avila | L74: =H74 -> 5563.56 | M74: =DATE(2018,12,31)-I74 -> 185
B75: Oklahoma | C75: 829.0182 | D75: Oklahoma | E75: 829.0182 | G75: Amy Cox | H75: 5527.846 | I75: 43453 | K75: =G75 -> Amy Cox | L75: =H75 -> 5527.846 | M75: =DATE(2018,12,31)-I75 -> 12
B76: Florida | C76: 750.7424 | D76: Florida | E76: 750.7424 | G76: Andy Reiter | H76: 6608.448 | I76: 43458 | K76: =G76 -> Andy Reiter | L76: =H76 -> 6608.448 | M76: =DATE(2018,12,31)-I76 -> 7
B77: South Dakota | C77: 682.5542 | D77: South Dakota | E77: 682.5542 | G77: Anna Häberlin | H77: 7888.294 | I77: 43054 | K77: =G77 -> Anna Häberlin | L77: =H77 -> 7888.294 | M77: =DATE(2018,12,31)-I77 -> 411
B78: Mississippi | C78: 550.6659 | D78: Mississippi | E78: 550.6659 | G78: Anne Mcfarland | H78: 5664.022 | I78: 43302 | K78: =G78 -> Anne Mcfarland | L78: =H78 -> 5664.022 | M78: =DATE(2018,12,31)-I78 -> 163
B79: Connecticut | C79: 533.4987 | D79: Connecticut | E79: 533.4987 | G79: Becky Martin | H79: 11789.63 | I79: 43157 | K79: =G79 -> Becky Martin | L79: =H79 -> 11789.63 | M79: =DATE(2018,12,31)-I79 -> 308
B80: District Of Columbia | C80: 490.9567 | D80: District Of Columbia | E80: 490.9567 | G80: Ben Ferrer | H80: 5907.972 | I80: 43448 | K80: =G80 -> Ben Ferrer | L80: =H80 -> 5907.972 | M80: =DATE(2018,12,31)-I80 -> 17
B81: Maryland | C81: 436.6492 | D81: Maryland | E81: 436.6492 | G81: Bill Donatelli | H81: 5718.521 | I81: 43431 | K81: =G81 -> Bill Donatelli | L81: =H81 -> 5718.521 | M81: =DATE(2018,12,31)-I81 -> 34
B82: Nevada | C82: 278.0678 | D82: Nevada | E82: 278.0678 | G82: Bill Shonely | H82: 10501.653 | I82: 42906 | K82: =G82 -> Bill Shonely | L82: =H82 -> 10501.653 | M82: =DATE(2018,12,31)-I82 -> 559
... B87: Grand Total | C87: 286397.02 | D87: Grand Total | E87: 286397.02 | G87: Cassandra Brandow | H87: 6076.139 | I87: 43417 | K87: =G87 -> Cassandra Brandow | L87: =H87 -> 6076.139 | M87: =DATE(2018,12,31)-I87 -> 48
G88: Christine Phan | H88: 5888.275 | I88: 43304 | K88: =G88 -> Christine Phan | L88: =H88 -> 5888.275 | M88: =DATE(2018,12,31)-I88 -> 161
G89: Christopher Conant | H89: 12129.072 | I89: 43421 | K89: =G89 -> Christopher Conant | L89: =H89 -> 12129.072 | M89: =DATE(2018,12,31)-I89 -> 44
G90: Christopher Martinez | H90: 8954.02 | I90: 43427 | K90: =G90 -> Christopher Martinez | L90: =H90 -> 8954.02 | M90: =DATE(2018,12,31)-I90 -> 38
G91: Cindy Stewart | H91: 5690.055 | I91: 43406 | K91: =G91 -> Cindy Stewart | L91: =H91 -> 5690.055 | M91: =DATE(2018,12,31)-I91 -> 59
B92: Segment | C92: At Risk | G92: Clay Ludtke | H92: 10880.546 | I92: 43180 | K92: =G92 -> Clay Ludtke | L92: =H92 -> 10880.546 | M92: =DATE(2018,12,31)-I92 -> 285
G93: Corinna Mitchell | H93: 6339.5576 | I93: 43437 | K93: =G93 -> Corinna Mitchell | L93: =H93 -> 6339.5576 | M93: =DATE(2018,12,31)-I93 -> 28
B94: Row Labels | C94: Total Revenue | D94: Max Order Date | G94: Dan Reichenbach | H94: 6528.034 | I94: 43461 | K94: =G94 -> Dan Reichenbach | L94: =H94 -> 6528.034 | M94: =DATE(2018,12,31)-I94 -> 4
B95: Lauren Leatherbury | C95: 2741.204 | D95: 43215 | G95: Daniel Raglin | H95: 8350.868 | I95: 43414 | K95: =G95 -> Daniel Raglin | L95: =H95 -> 8350.868 | M95: =DATE(2018,12,31)-I95 -> 51
B96: John Lucas | C96: 2725.256 | D96: 42850 | G96: Darrin Martin | H96: 6345.103 | I96: 43407 | K96: =G96 -> Darrin Martin | L96: =H96 -> 6345.103 | M96: =DATE(2018,12,31)-I96 -> 58
B97: Bill Overfelt | C97: 2682.728 | D97: 43327 | G97: Dean Percer | H97: 7198.761 | I97: 43380 | K97: =G97 -> Dean Percer | L97: =H97 -> 7198.761 | M97: =DATE(2018,12,31)-I97 -> 85
B98: Nicole Hansen | C98: 2673.29 | D98: 43275 | G98: Dennis Pardue | H98: 5480.724 | I98: 43106 | K98: =G98 -> Dennis Pardue | L98: =H98 -> 5480.724 | M98: =DATE(2018,12,31)-I98 -> 359
B99: Beth Thompson | C99: 2567.656 | D99: 43128 | G99: Edward Hooks | H99: 10310.88 | I99: 43329 | K99: =G99 -> Edward Hooks | L99: =H99 -> 10310.88 | M99: =DATE(2018,12,31)-I99 -> 136
B100: Eleni Mccrary | C100: 2567.01 | D100: 43332 | G100: Emily Phan | H100: 5478.0608 | I100: 43452 | K100: =G100 -> Emily Phan | L100: =H100 -> 5478.0608 | M100: =DATE(2018,12,31)-I100 -> 13
B101: Mary Zewe | C101: 2564.906 | D101: 43182 | G101: Fred Hopkins | H101: 6987.196 | I101: 43459 | K101: =G101 -> Fred Hopkins | L101: =H101 -> 6987.196 | M101: =DATE(2018,12,31)-I101 -> 6
B102: Deanra Eno | C102: 2550.874 | D102: 42746 | G102: Grace Kelly | H102: 6497.27 | I102: 43352 | K102: =G102 -> Grace Kelly | L102: =H102 -> 6497.27 | M102: =DATE(2018,12,31)-I102 -> 113
B103: Amy Hunt | C103: 2495.3916 | D103: 43234 | G103: Grant Thornton | H103: 9351.212 | I103: 43408 | K103: =G103 -> Grant Thornton | L103: =H103 -> 9351.212 | M103: =DATE(2018,12,31)-I103 -> 57
B104: Charles Crestani | C104: 2471.65 | D104: 43358 | G104: Greg Maxwell | H104: 6049.966 | I104: 43347 | K104: =G104 -> Greg Maxwell | L104: =H104 -> 6049.966 | M104: =DATE(2018,12,31)-I104 -> 118
G105: Greg Tran | H105: 11820.12 | I105: 43428 | K105: =G105 -> Greg Tran | L105: =H105 -> 11820.12 | M105: =DATE(2018,12,31)-I105 -> 37
G106: Harry Marie | H106: 8236.7648 | I106: 43462 | K106: =G106 -> Harry Marie | L106: =H106 -> 8236.7648 | M106: =DATE(2018,12,31)-I106 -> 3
G107: Helen Wasserman | H107: 9300.254 | I107: 43347 | K107: =G107 -> Helen Wasserman | L107: =H107 -> 9300.254 | M107: =DATE(2018,12,31)-I107 -> 118
G108: Hunter Lopez | H108: 12873.298 | I108: 43421 | K108: =G108 -> Hunter Lopez | L108: =H108 -> 12873.298 | M108: =DATE(2018,12,31)-I108 -> 44
G109: James Galang | H109: 6366.392 | I109: 43463 | K109: =G109 -> James Galang | L109: =H109 -> 6366.392 | M109: =DATE(2018,12,31)-I109 -> 2
G110: Jane Waco | H110: 7721.714 | I110: 43422 | K110: =G110 -> Jane Waco | L110: =H110 -> 7721.714 | M110: =DATE(2018,12,31)-I110 -> 43
G111: Jim Epp | H111: 7754.976 | I111: 43416 | K111: =G111 -> Jim Epp | L111: =H111 -> 7754.976 | M111: =DATE(2018,12,31)-I111 -> 49
G112: Joe Elijah | H112: 8697.843 | I112: 43418 | K112: =G112 -> Joe Elijah | L112: =H112 -> 8697.843 | M112: =DATE(2018,12,31)-I112 -> 47
G113: Joel Eaton | H113: 6760.815 | I113: 43413 | K113: =G113 -> Joel Eaton | L113: =H113 -> 6760.815 | M113: =DATE(2018,12,31)-I113 -> 52
...
